chicagorecoverypy/__init__.py
chicagorecoverypy/schemas.py
chicagorecoverypy/utils.py
chicagorecoverypy/value_sets.py
chicagorecoverypy/workbook.py
chicagorecoverypy/processors/__init__.py
chicagorecoverypy/processors/core.py
chicagorecoverypy/processors/reporting.py
chicagorecoverypy-0.1.5.dist-info/LICENSE
chicagorecoverypy-0.1.5.dist-info/METADATA
chicagorecoverypy-0.1.5.dist-info/WHEEL
chicagorecoverypy-0.1.5.dist-info/entry_points.txt
chicagorecoverypy-0.1.5.dist-info/top_level.txt
chicagorecoverypy-0.1.5.dist-info/RECORD
